harness_py_sdk/ __init__.py
harness_py_sdk/harness_connectors.py
harness_py_sdk/harness_old_connectors.py
harness_py_sdk/harness_pipelines.py
harness_py_sdk/harness_services.py
harness_py_sdk/harness_templates.py
harness_py_sdk/sdk.py
harness_py_sdk-0.0.12.dist-info/METADATA
harness_py_sdk-0.0.12.dist-info/WHEEL
harness_py_sdk-0.0.12.dist-info/licenses/LICENSE
harness_py_sdk-0.0.12.dist-info/RECORD
