Metadata-Version: 2.3
Name: harness-py-sdk
Version: 0.0.12
Summary: This is a non-official package that leverages the Harness API using Python.
Project-URL: Homepage, https://github.com/guilhermezanini-harness/harness-py-sdk
Project-URL: Issues, https://github.com/guilhermezanini-harness/harness-py-sdk/issues
Author-email: Guilherme Zanini <guilherme.zanini@harness.io>
License-File: LICENSE
Classifier: License :: OSI Approved :: MIT License
Classifier: Operating System :: OS Independent
Classifier: Programming Language :: Python :: 3
Requires-Python: >=3.8
